{
  "gdna": {
    "1.0": {
      "description": "genomic DNA",
      "properties": {
        "name": "genomic DNA",
        "volume": "",
        "volume_units": "",
        "comments": "","lab_code":""
      },
      "expected_inputs": [],
      "singleton": "0",
      "expected_outputs": [],
      "actions": {},
      "instantiation_layouts": [],
      "cogs" : {
        "state" : "active",
        "cost" : "0.00",
        "cost_split_by_children" : [{"*/*/*/*":{}}],
        "allocation_type" : ""
      }
    }
  },
  "cfdna": {
    "1.0": {
      "description": "cell free DNA ",
      "singleton": "0",
      "properties": {
        "name": "cfDNA",
        "volume": "",
        "volume_units": "",
        "comments": "","lab_code":""
      },
      "expected_inputs": [],
      "expected_outputs": [],
      "actions": {},
      "instantiation_layouts": [],
      "cogs" : {
        "state" : "active",
        "cost" : "0.00",
        "cost_split_by_children" : [{"*/*/*/*":{}}],
        "allocation_type" : ""
      }
    }
  },
  "blood-plasma": {
    "1.0": {
      "description": "plasma (whole blood)",
      "singleton": "0",
      "properties": {
        "name": "plasma (whole blood)",
        "volume": "",
        "volume_units": "",
        "comments": "",
        "lab_code":""
      },
      "expected_inputs": [],
      "expected_outputs": [],
      "actions": {},
      "instantiation_layouts": [],
      "cogs" : {
        "state" : "active",
        "cost" : "0.00",
        "cost_split_by_children" : [{"*/*/*/*":{}}],
        "allocation_type" : ""
      }
    }
  }
}
